faker_commerce/__init__.py
faker_commerce-1.0.4.dist-info/LICENSE
faker_commerce-1.0.4.dist-info/METADATA
faker_commerce-1.0.4.dist-info/WHEEL
faker_commerce-1.0.4.dist-info/top_level.txt
faker_commerce-1.0.4.dist-info/RECORD
