Metadata-Version: 2.1
Name: faker-commerce
Version: 1.0.4
Summary: Provider for Faker which adds fake commerce product names, prices, categories and descriptions.
Home-page: https://github.com/nicobritos/python-faker-commerce
Author: Nicolas Ignacio Britos
Author-email: nicbritos@hotmail.com
License: UNKNOWN
Platform: UNKNOWN
Classifier: Programming Language :: Python :: 3.6
Classifier: Programming Language :: Python :: 3.7
Classifier: Programming Language :: Python :: 3.8
Classifier: License :: OSI Approved :: MIT License
Classifier: Operating System :: OS Independent
License-File: LICENSE
